exasol_python_test_framework/__init__.py
exasol_python_test_framework/docker_db_environment/__init__.py
exasol_python_test_framework/exatest/__init__.py
exasol_python_test_framework/exatest/clients/__init__.py
exasol_python_test_framework/exatest/clients/client_setup.py
exasol_python_test_framework/exatest/clients/odbc.py
exasol_python_test_framework/exatest/servers/__init__.py
exasol_python_test_framework/exatest/servers/__main__.py
exasol_python_test_framework/exatest/servers/_compat.py
exasol_python_test_framework/exatest/servers/authorizers.py
exasol_python_test_framework/exatest/servers/filesystems.py
exasol_python_test_framework/exatest/servers/handlers.py
exasol_python_test_framework/exatest/servers/ioloop.py
exasol_python_test_framework/exatest/servers/log.py
exasol_python_test_framework/exatest/test/__init__.py
exasol_python_test_framework/exatest/testcase.py
exasol_python_test_framework/exatest/threading.py
exasol_python_test_framework/exatest/utils.py
exasol_python_test_framework/performance/__init__.py
exasol_python_test_framework/udf/__init__.py
exasol_python_test_framework/udf/available_python_packages_utils.py
exasol_python_test_framework/udf/udf_debug.py
exasol_python_test_framework-0.6.1.dist-info/LICENSE
exasol_python_test_framework-0.6.1.dist-info/WHEEL
exasol_python_test_framework-0.6.1.dist-info/METADATA
exasol_python_test_framework-0.6.1.dist-info/RECORD
